coverme.py
coverme-0.8.1.dist-info/LICENSE
coverme-0.8.1.dist-info/METADATA
coverme-0.8.1.dist-info/WHEEL
coverme-0.8.1.dist-info/entry_points.txt
coverme-0.8.1.dist-info/top_level.txt
coverme-0.8.1.dist-info/RECORD
