Metadata-Version: 2.1
Name: coverme
Version: 0.8.1
Summary: Lightweight and easy configurable server backup utility.
Author-email: Alexey Kinëv <rudy@05bit.com>
License: Apache-2.0
Project-URL: Homepage, https://github.com/05bit/coverme
Project-URL: Bug Tracker, https://github.com/05bit/coverme/issues
Keywords: backup,utility,aws,devops
Classifier: Development Status :: 3 - Alpha
Classifier: Environment :: Console
Classifier: Environment :: Web Environment
Classifier: Intended Audience :: Developers
Classifier: License :: OSI Approved :: Apache Software License
Classifier: Programming Language :: Python :: 2.7
Classifier: Programming Language :: Python :: 3
Requires-Python: >=3.7
License-File: LICENSE
Requires-Dist: click >=7.0.0
Requires-Dist: pyyaml >=6.0.0
Requires-Dist: boto3 >=1.28.0
Provides-Extra: dotenv
Requires-Dist: python-dotenv >=1.0.0 ; extra == 'dotenv'
